stego_llm/__init__.py
stego_llm/cli.py
stego_llm/log.py
stego_llm/core/__init__.py
stego_llm/core/decoder.py
stego_llm/core/encoder.py
stego_llm/core/trace.py
stego_llm/crypto/__init__.py
stego_llm/crypto/bitcoin.py
stego_llm/examples/__init__.py
stego_llm/examples/basic_demo.py
stego_llm/llm/__init__.py
stego_llm/llm/interface.py
stego_llm/llm/mock.py
stego_llm/llm/utilities.py
stego_llm/steganography/__init__.py
stego_llm/steganography/codecs.py
stego_llm/steganography/filters.py
innocuous-0.2.4.dist-info/METADATA
innocuous-0.2.4.dist-info/WHEEL
innocuous-0.2.4.dist-info/entry_points.txt
innocuous-0.2.4.dist-info/licenses/LICENSE.txt
innocuous-0.2.4.dist-info/RECORD
