Metadata-Version: 2.4
Name: innocuous
Version: 0.2.4
Summary: LLM steganography: encode and decode data in generated text
Project-URL: Homepage, https://github.com/sutt/innocuous
Author-email: Will Sutton <wsutton17@gmail.com>
License: MIT
License-File: LICENSE.txt
Requires-Python: >=3.12
Requires-Dist: llama-cpp-python>=0.3.16
Provides-Extra: dev
Requires-Dist: ipykernel>=6.30.1; extra == 'dev'
Requires-Dist: pytest-mock; extra == 'dev'
Requires-Dist: pytest>=8.4.1; extra == 'dev'
